tap_teamwork/__init__.py
tap_teamwork/schemas/categories.json
tap_teamwork/schemas/companies.json
tap_teamwork/schemas/latest_activity.json
tap_teamwork/schemas/milestones.json
tap_teamwork/schemas/people.json
tap_teamwork/schemas/project_custom_fields.json
tap_teamwork/schemas/project_updates.json
tap_teamwork/schemas/projects.json
tap_teamwork/schemas/risks.json
tap_teamwork/schemas/tags.json
tap_teamwork/schemas/tasks.json
tap_teamwork/streams.py
tap_teamwork/tap.py
tap_teamwork/tests/__init__.py
tap_teamwork/tests/test_core.py
tap_teamwork-0.3.4.dist-info/entry_points.txt
tap_teamwork-0.3.4.dist-info/LICENSE
tap_teamwork-0.3.4.dist-info/WHEEL
tap_teamwork-0.3.4.dist-info/METADATA
tap_teamwork-0.3.4.dist-info/RECORD
