Metadata-Version: 2.1
Name: tap-teamwork
Version: 0.3.4
Summary: Singer.io tap for Teamwork.com
Home-page: https://github.com/immuta/tap-teamwork
License: MIT
Keywords: singer,elt,replication
Author: Stephen Bailey
Author-email: stkbailey@gmail.com
Requires-Python: >=3.8,<3.9
Classifier: Development Status :: 4 - Beta
Classifier: License :: OSI Approved :: MIT License
Classifier: Programming Language :: Python :: 3
Classifier: Programming Language :: Python :: 3 :: Only
Classifier: Programming Language :: Python :: 3.8
Classifier: Topic :: Database
Requires-Dist: singer-sdk (>=0.1.3,<0.2.0)
Project-URL: Repository, https://github.com/immuta/tap-teamwork
